{
    "format_version": "1.12.0",
    "minecraft:geometry": [{
        "description": {
            "identifier": "geometry.lil_pineapple",
            "texture_width": 32,
            "texture_height": 32,
            "visible_bounds_width": 2,
            "visible_bounds_height": 2.5,
            "visible_bounds_offset": [
                0,
                0.75,
                0
            ]
        },
        "bones": [{
                "name": "bb_main",
                "pivot": [
                    0,
                    0,
                    0
                ],
                "cubes": [{
                    "origin": [-4,
                        1, -5
                    ],
                    "size": [
                        8,
                        7,
                        0
                    ],
                    "uv": {
                        "north": {
                            "uv": [
                                24,
                                4
                            ],
                            "uv_size": [
                                8,
                                7
                            ]
                        },
                        "east": {
                            "uv": [
                                0,
                                0
                            ],
                            "uv_size": [
                                0,
                                7
                            ]
                        },
                        "west": {
                            "uv": [
                                0,
                                0
                            ],
                            "uv_size": [
                                0,
                                7
                            ]
                        },
                        "up": {
                            "uv": [
                                8,
                                0
                            ],
                            "uv_size": [-8,
                                0
                            ]
                        },
                        "down": {
                            "uv": [
                                8,
                                0
                            ],
                            "uv_size": [-8,
                                0
                            ]
                        }
                    }
                }]
            },
            {
                "name": "bd",
                "pivot": [
                    4.5, -0.5,
                    2.5
                ],
                "cubes": [{
                        "origin": [-1.5,
                            7, -0.5
                        ],
                        "size": [
                            1,
                            3,
                            1
                        ],
                        "pivot": [
                            8.5, -0.5,
                            2.5
                        ],
                        "rotation": [
                            0,
                            0,
                            5
                        ],
                        "uv": {
                            "north": {
                                "uv": [
                                    18,
                                    0
                                ],
                                "uv_size": [
                                    1,
                                    3
                                ]
                            },
                            "east": {
                                "uv": [
                                    18,
                                    3
                                ],
                                "uv_size": [
                                    1,
                                    3
                                ]
                            },
                            "south": {
                                "uv": [
                                    18,
                                    6
                                ],
                                "uv_size": [
                                    1,
                                    3
                                ]
                            },
                            "west": {
                                "uv": [
                                    18,
                                    9
                                ],
                                "uv_size": [
                                    1,
                                    3
                                ]
                            },
                            "up": {
                                "uv": [
                                    18,
                                    12
                                ],
                                "uv_size": [
                                    1,
                                    1
                                ]
                            }
                        }
                    },
                    {
                        "origin": [-4.5,
                            0, -4.5
                        ],
                        "size": [
                            9,
                            8,
                            9
                        ],
                        "uv": {
                            "north": {
                                "uv": [
                                    9,
                                    0
                                ],
                                "uv_size": [
                                    9,
                                    8
                                ]
                            },
                            "east": {
                                "uv": [
                                    9,
                                    8
                                ],
                                "uv_size": [
                                    9,
                                    8
                                ]
                            },
                            "south": {
                                "uv": [
                                    9,
                                    16
                                ],
                                "uv_size": [
                                    9,
                                    8
                                ]
                            },
                            "west": {
                                "uv": [
                                    0,
                                    18
                                ],
                                "uv_size": [
                                    9,
                                    8
                                ]
                            },
                            "up": {
                                "uv": [
                                    0,
                                    0
                                ],
                                "uv_size": [
                                    9,
                                    9
                                ]
                            },
                            "down": {
                                "uv": [
                                    0,
                                    18
                                ],
                                "uv_size": [
                                    9, -9
                                ]
                            }
                        }
                    }
                ]
            }
        ]
    }]
}